sygaldry/__init__.py
sygaldry/artificery.py
sygaldry/environment.py
sygaldry-0.0.1.dist-info/LICENSE
sygaldry-0.0.1.dist-info/WHEEL
sygaldry-0.0.1.dist-info/METADATA
sygaldry-0.0.1.dist-info/RECORD
