Metadata-Version: 2.1
Name: sygaldry
Version: 0.0.1
Summary: It's Sygaldry
Author-email: "Rohan B. Dalton" <rohan@rohandalton.io>
Classifier: License :: OSI Approved :: MIT License
Project-URL: Home, https://github.com/RohanDalton/sygaldry
